setup.py
DeSW.egg-info/PKG-INFO
DeSW.egg-info/SOURCES.txt
DeSW.egg-info/dependency_links.txt
DeSW.egg-info/requires.txt
DeSW.egg-info/top_level.txt
desw/__init__.py
desw/plugin.py
desw/server.py
desw/static/swagger.json
test/test_account.py
test/test_processing.py
test/test_server.py