Metadata-Version: 1.1
Name: DeSW
Version: 0.0.3
Summary: A centralized ledger suitable for use like a cryptocurrency hot wallet.
Home-page: https://github.com/WalletGuild/desw
Author: WalletGuild
Author-email: support@gitguild.com
License: MIT
Platform: UNKNOWN
Classifier: License :: OSI Approved :: MIT License
Classifier: Programming Language :: Python :: 2
Classifier: Topic :: Software Development :: Libraries
